termol/__init__.py
termol/canvas.py
termol/cli.py
termol/render.py
termol/smiles_1000.csv
termol/utilities.py
termol-0.1.7.dist-info/licenses/LICENSE
termol-0.1.7.dist-info/METADATA
termol-0.1.7.dist-info/WHEEL
termol-0.1.7.dist-info/entry_points.txt
termol-0.1.7.dist-info/top_level.txt
termol-0.1.7.dist-info/RECORD
