Metadata-Version: 2.4
Name: termol
Version: 0.1.7
Summary: A simple molecular renderer for the terminal using RDKit.
Home-page: https://github.com/Nicholas-Freitas/TerMol
Author: Nicholas Freitas
Author-email: Nicholas.Freitas@ucsf.edu
Classifier: Programming Language :: Python :: 3
Classifier: License :: OSI Approved :: MIT License
Classifier: Operating System :: OS Independent
Requires-Python: >=3.9
License-File: LICENSE
Requires-Dist: numpy<=2.2.6
Requires-Dist: rdkit<=2025.3.3
Dynamic: author
Dynamic: author-email
Dynamic: classifier
Dynamic: description
Dynamic: description-content-type
Dynamic: home-page
Dynamic: license-file
Dynamic: requires-dist
Dynamic: requires-python
Dynamic: summary
